{
  "parent": "minecraft:recipes/root",
  "criteria": {
    "has_raw_iron_disulfide": {
      "conditions": {
        "items": [
          {
            "items": [
              "steelmod:raw_iron_disulfide"
            ]
          }
        ]
      },
      "trigger": "minecraft:inventory_changed"
    },
    "has_the_recipe": {
      "conditions": {
        "recipe": "steelmod:iron_ingot_from_blasting_raw_iron_disulfide"
      },
      "trigger": "minecraft:recipe_unlocked"
    }
  },
  "requirements": [
    [
      "has_raw_iron_disulfide",
      "has_the_recipe"
    ]
  ],
  "rewards": {
    "recipes": [
      "steelmod:iron_ingot_from_blasting_raw_iron_disulfide"
    ]
  },
  "sends_telemetry_event": false
}